personalization_profiles/AdventurousTraveler.py
personalization_profiles/BudgetTraveler.py
personalization_profiles/BusinessTraveler.py
personalization_profiles/EcoTraveler.py
personalization_profiles/FamilyTraveler.py
personalization_profiles/PersonaManager.py
personalization_profiles/PersonaType.py
personalization_profiles/PersonalizationProfile.py
personalization_profiles/User.py
personalization_profiles/__init__.py
PersonalizationProfiles-0.1.2.dist-info/METADATA
PersonalizationProfiles-0.1.2.dist-info/WHEEL
PersonalizationProfiles-0.1.2.dist-info/top_level.txt
PersonalizationProfiles-0.1.2.dist-info/RECORD
