Metadata-Version: 2.1
Name: PersonalizationProfiles
Version: 0.1.2
License: MIT
Requires-Python: >=3.9
Requires-Dist: numpy >=1.20
